django_saml/__init__.py
django_saml/apps.py
django_saml/backends.py
django_saml/exceptions.py
django_saml/settings.py
django_saml/urls.py
django_saml/views.py
python3_saml_django-1.3.0.dist-info/LICENSE
python3_saml_django-1.3.0.dist-info/METADATA
python3_saml_django-1.3.0.dist-info/WHEEL
python3_saml_django-1.3.0.dist-info/top_level.txt
python3_saml_django-1.3.0.dist-info/RECORD
